{"subregions":{"type":"FeatureCollection","properties":{"CONTINENT":"Asia","REGION":"South-Eastern Asia","NAME_2":"Zambales","NAME_1":"Region III (Central Luzon)","NAME_0":"Philippines","ISO":"PHL","ID_2_OR":3790000000,"ID_1_OR":3000000000},"features":[{"type":"Feature","properties":{"ID_0":177,"ISO":"PHL","NAME_0":"Philippines","ID_2_OR":3790000000,"NAME_2":"Zambales","ID_3_OR":3791562000,"NAME_3":"Botolan","NL_NAME_3":null,"VARNAME_3":null,"TYPE_3":"Bayan|Munisipyo","ENGTYPE_2":"Municipality","X_COORD":120.20010500500001,"Y_COORD":15.2297323407},"geometry":{"type":"Polygon","coordinates":[]}},{"type":"Feature","properties":{"ID_0":177,"ISO":"PHL","NAME_0":"Philippines","ID_2_OR":3790000000,"NAME_2":"Zambales","ID_3_OR":3791563000,"NAME_3":"Cabangan","NL_NAME_3":null,"VARNAME_3":null,"TYPE_3":"Bayan|Munisipyo","ENGTYPE_2":"Municipality","X_COORD":120.12289297599997,"Y_COORD":15.1611175287},"geometry":{"type":"Polygon","coordinates":[]}},{"type":"Feature","properties":{"ID_0":177,"ISO":"PHL","NAME_0":"Philippines","ID_2_OR":3790000000,"NAME_2":"Zambales","ID_3_OR":3791564000,"NAME_3":"Candelaria","NL_NAME_3":null,"VARNAME_3":null,"TYPE_3":"Bayan|Munisipyo","ENGTYPE_2":"Municipality","X_COORD":120.08340995900001,"Y_COORD":15.637694418100002},"geometry":{"type":"MultiPolygon","coordinates":[]}},{"type":"Feature","properties":{"ID_0":177,"ISO":"PHL","NAME_0":"Philippines","ID_2_OR":3790000000,"NAME_2":"Zambales","ID_3_OR":3791565000,"NAME_3":"Castillejos","NL_NAME_3":null,"VARNAME_3":null,"TYPE_3":"Bayan|Munisipyo","ENGTYPE_2":"Municipality","X_COORD":120.217706273,"Y_COORD":14.9419444968},"geometry":{"type":"Polygon","coordinates":[]}},{"type":"Feature","properties":{"ID_0":177,"ISO":"PHL","NAME_0":"Philippines","ID_2_OR":3790000000,"NAME_2":"Zambales","ID_3_OR":3791566000,"NAME_3":"Iba","NL_NAME_3":null,"VARNAME_3":null,"TYPE_3":"Bayan|Munisipyo","ENGTYPE_2":"Municipality","X_COORD":120.050173155,"Y_COORD":15.376307258600004},"geometry":{"type":"Polygon","coordinates":[]}},{"type":"Feature","properties":{"ID_0":177,"ISO":"PHL","NAME_0":"Philippines","ID_2_OR":3790000000,"NAME_2":"Zambales","ID_3_OR":3791567000,"NAME_3":"Masinloc","NL_NAME_3":null,"VARNAME_3":null,"TYPE_3":"Bayan|Munisipyo","ENGTYPE_2":"Municipality","X_COORD":120.053542606,"Y_COORD":15.534584636900002},"geometry":{"type":"MultiPolygon","coordinates":[]}},{"type":"Feature","properties":{"ID_0":177,"ISO":"PHL","NAME_0":"Philippines","ID_2_OR":3790000000,"NAME_2":"Zambales","ID_3_OR":3791568000,"NAME_3":"Olongapo City","NL_NAME_3":null,"VARNAME_3":null,"TYPE_3":"Lungsod|Siyudad","ENGTYPE_2":"City","X_COORD":120.342631064,"Y_COORD":14.886230525100002},"geometry":{"type":"Polygon","coordinates":[]}},{"type":"Feature","properties":{"ID_0":177,"ISO":"PHL","NAME_0":"Philippines","ID_2_OR":3790000000,"NAME_2":"Zambales","ID_3_OR":3791569000,"NAME_3":"Palauig","NL_NAME_3":null,"VARNAME_3":null,"TYPE_3":"Bayan|Munisipyo","ENGTYPE_2":"Municipality","X_COORD":120.04185972600001,"Y_COORD":15.452157459600002},"geometry":{"type":"MultiPolygon","coordinates":[]}},{"type":"Feature","properties":{"ID_0":177,"ISO":"PHL","NAME_0":"Philippines","ID_2_OR":3790000000,"NAME_2":"Zambales","ID_3_OR":3791570000,"NAME_3":"San Antonio","NL_NAME_3":null,"VARNAME_3":null,"TYPE_3":"Bayan|Munisipyo","ENGTYPE_2":"Municipality","X_COORD":120.109767489,"Y_COORD":14.8753614072},"geometry":{"type":"MultiPolygon","coordinates":[]}},{"type":"Feature","properties":{"ID_0":177,"ISO":"PHL","NAME_0":"Philippines","ID_2_OR":3790000000,"NAME_2":"Zambales","ID_3_OR":3791571000,"NAME_3":"San Felipe","NL_NAME_3":null,"VARNAME_3":null,"TYPE_3":"Bayan|Munisipyo","ENGTYPE_2":"Municipality","X_COORD":120.12610605199998,"Y_COORD":15.073845688500002},"geometry":{"type":"Polygon","coordinates":[]}},{"type":"Feature","properties":{"ID_0":177,"ISO":"PHL","NAME_0":"Philippines","ID_2_OR":3790000000,"NAME_2":"Zambales","ID_3_OR":3791572000,"NAME_3":"San Marcelino","NL_NAME_3":null,"VARNAME_3":null,"TYPE_3":"Bayan|Munisipyo","ENGTYPE_2":"Municipality","X_COORD":120.282349226,"Y_COORD":15.027101519999999},"geometry":{"type":"Polygon","coordinates":[]}},{"type":"Feature","properties":{"ID_0":177,"ISO":"PHL","NAME_0":"Philippines","ID_2_OR":3790000000,"NAME_2":"Zambales","ID_3_OR":3791573000,"NAME_3":"San Narciso","NL_NAME_3":null,"VARNAME_3":null,"TYPE_3":"Bayan|Munisipyo","ENGTYPE_2":"Municipality","X_COORD":120.11172294100001,"Y_COORD":15.012190576100002},"geometry":{"type":"Polygon","coordinates":[]}},{"type":"Feature","properties":{"ID_0":177,"ISO":"PHL","NAME_0":"Philippines","ID_2_OR":3790000000,"NAME_2":"Zambales","ID_3_OR":3791574000,"NAME_3":"Santa Cruz","NL_NAME_3":null,"VARNAME_3":null,"TYPE_3":"Bayan|Munisipyo","ENGTYPE_2":"Municipality","X_COORD":120.034001577,"Y_COORD":15.760221427199998},"geometry":{"type":"MultiPolygon","coordinates":[]}},{"type":"Feature","properties":{"ID_0":177,"ISO":"PHL","NAME_0":"Philippines","ID_2_OR":3790000000,"NAME_2":"Zambales","ID_3_OR":3791575000,"NAME_3":"Subic","NL_NAME_3":null,"VARNAME_3":null,"TYPE_3":"Bayan|Munisipyo","ENGTYPE_2":"Municipality","X_COORD":120.26286327400001,"Y_COORD":14.895139026600004},"geometry":{"type":"MultiPolygon","coordinates":[]}}]},"roads":{"type":"FeatureCollection","properties":{"CONTINENT":"Asia","REGION":"South-Eastern Asia","NAME_2":"Zambales","NAME_1":"Region III (Central Luzon)","NAME_0":"Philippines","ISO":"PHL","ID_2_OR":3790000000,"ID_1_OR":3000000000},"features":[]}}